resonitepy/__init__.py
resonitepy/classes.py
resonitepy/client.py
resonitepy/endpoints.py
resonitepy/exceptions.py
resonitepy/secrets.py
resonitepy/utils.py
resonitepy-0.0.1.dist-info/METADATA
resonitepy-0.0.1.dist-info/WHEEL
resonitepy-0.0.1.dist-info/entry_points.txt
resonitepy-0.0.1.dist-info/licenses/LICENCE
resonitepy-0.0.1.dist-info/RECORD
