Metadata-Version: 2.4
Name: resonitepy
Version: 0.0.1
Summary: Unofficial Resonite API python library.
License: MIT
License-File: LICENCE
Author: brodokk
Author-email: brodokk@brodokk.space
Requires-Python: >=3.10
Classifier: License :: OSI Approved :: MIT License
Classifier: Programming Language :: Python :: 3
Classifier: Programming Language :: Python :: 3.10
Classifier: Programming Language :: Python :: 3.11
Classifier: Programming Language :: Python :: 3.12
Classifier: Programming Language :: Python :: 3.13
Classifier: Programming Language :: Python :: 3.14
Requires-Dist: dacite (>=1.6.0,<2.0.0)
Requires-Dist: python-dateutil (>=2.8.2,<3.0.0)
Requires-Dist: requests (>=2.28.1,<3.0.0)
Project-URL: Homepage, https://github.com/brodokk/resonitepy
Project-URL: Repository, https://github.com/brodokk/resonitepy
